README
setup.py
TelAPI.egg-info/SOURCES.txt
telapi/__init__.py
telapi/utils.py
telapi.egg-info/PKG-INFO
telapi.egg-info/SOURCES.txt
telapi.egg-info/dependency_links.txt
telapi.egg-info/requires.txt
telapi.egg-info/top_level.txt
telapi/inboundxml/__init__.py
telapi/rest/__init__.py
telapi/rest/exceptions.py
telapi/schema/__init__.py