Metadata-Version: 1.0
Name: telapi
Version: 0.1.7
Summary: TelAPI REST API client and InboundXML generator
Home-page: https://github.com/telapi/telapi-python/
Author: TelAPI
Author-email: help@telapi.com
License: UNKNOWN
Keywords: telapi,inboundxml,telephony,rest
Platform: UNKNOWN
Classifier: Programming Language :: Python
Classifier: Operating System :: OS Independent
Classifier: License :: OSI Approved :: MIT License
Classifier: Intended Audience :: Developers
Classifier: Development Status :: 4 - Beta
Classifier: Topic :: Software Development :: Libraries :: Python Modules
Classifier: Topic :: Communications :: Telephony
